{"i":770150,"time":2110,"elements":[{"iceElevation":911.5172512812666,"bedElevation":0,"diffusivity_up":0,"flux_up":0,"diffusivity_down":0,"flux_down":0,"totalFlux":0,"massBalanceFlux":0,"iteration":0,"deltaH":0},{"iceElevation":910.906542181931,"bedElevation":0,"diffusivity_up":0,"flux_up":0,"diffusivity_down":0,"flux_down":0,"totalFlux":0,"massBalanceFlux":0,"iteration":0,"deltaH":0},{"iceElevation":910.13612420071,"bedElevation":0,"diffusivity_up":0,"flux_up":0,"diffusivity_down":0,"flux_down":0,"totalFlux":0,"massBalanceFlux":0,"iteration":0,"deltaH":0},{"iceElevation":909.2528801212932,"bedElevation":0,"diffusivity_up":0,"flux_up":0,"diffusivity_down":0,"flux_down":0,"totalFlux":0,"massBalanceFlux":0,"iteration":0,"deltaH":0},{"iceElevation":908.2790901242322,"bedElevation":0,"diffusivity_up":0,"flux_up":0,"diffusivity_down":0,"flux_down":0,"totalFlux":0,"massBalanceFlux":0,"iteration":0,"deltaH":0},{"iceElevation":907.228159916162,"bedElevation":0,"diffusivity_up":0,"flux_up":0,"diffusivity_down":0,"flux_down":0,"totalFlux":0,"massBalanceFlux":0,"iteration":0,"deltaH":0},{"iceElevation":906.1091580886924,"bedElevation":0,"diffusivity_up":0,"flux_up":0,"diffusivity_down":0,"flux_down":0,"totalFlux":0,"massBalanceFlux":0,"iteration":0,"deltaH":0},{"iceElevation":904.9286709829418,"bedElevation":0,"diffusivity_up":0,"flux_up":0,"diffusivity_down":0,"flux_down":0,"totalFlux":0,"massBalanceFlux":0,"iteration":0,"deltaH":0},{"iceElevation":903.6917163266245,"bedElevation":0,"diffusivity_up":0,"flux_up":0,"diffusivity_down":0,"flux_down":0,"totalFlux":0,"massBalanceFlux":0,"iteration":0,"deltaH":0},{"iceElevation":902.402250267969,"bedElevation":0,"diffusivity_up":0,"flux_up":0,"diffusivity_down":0,"flux_down":0,"totalFlux":0,"massBalanceFlux":0,"iteration":0,"deltaH":0},{"iceElevation":901.0634733367306,"bedElevation":0,"diffusivity_up":0,"flux_up":0,"diffusivity_down":0,"flux_down":0,"totalFlux":0,"massBalanceFlux":0,"iteration":0,"deltaH":0},{"iceElevation":899.6780269432589,"bedElevation":0,"diffusivity_up":0,"flux_up":0,"diffusivity_down":0,"flux_down":0,"totalFlux":0,"massBalanceFlux":0,"iteration":0,"deltaH":0},{"iceElevation":898.2481258238503,"bedElevation":0,"diffusivity_up":0,"flux_up":0,"diffusivity_down":0,"flux_down":0,"totalFlux":0,"massBalanceFlux":0,"iteration":0,"deltaH":0},{"iceElevation":896.7756508260036,"bedElevation":0,"diffusivity_up":0,"flux_up":0,"diffusivity_down":0,"flux_down":0,"totalFlux":0,"massBalanceFlux":0,"iteration":0,"deltaH":0},{"iceElevation":895.2622159951492,"bedElevation":0,"diffusivity_up":0,"flux_up":0,"diffusivity_down":0,"flux_down":0,"totalFlux":0,"massBalanceFlux":0,"iteration":0,"deltaH":0},{"iceElevation":893.7092183743061,"bedElevation":0,"diffusivity_up":0,"flux_up":0,"diffusivity_down":0,"flux_down":0,"totalFlux":0,"massBalanceFlux":0,"iteration":0,"deltaH":0},{"iceElevation":892.1178758040858,"bedElevation":0,"diffusivity_up":0,"flux_up":0,"diffusivity_down":0,"flux_down":0,"totalFlux":0,"massBalanceFlux":0,"iteration":0,"deltaH":0},{"iceElevation":890.4892561676603,"bedElevation":0,"diffusivity_up":0,"flux_up":0,"diffusivity_down":0,"flux_down":0,"totalFlux":0,"massBalanceFlux":0,"iteration":0,"deltaH":0},{"iceElevation":888.8243003943695,"bedElevation":0,"diffusivity_up":0,"flux_up":0,"diffusivity_down":0,"flux_down":0,"totalFlux":0,"massBalanceFlux":0,"iteration":0,"deltaH":0},{"iceElevation":887.1238408175889,"bedElevation":0,"diffusivity_up":0,"flux_up":0,"diffusivity_down":0,"flux_down":0,"totalFlux":0,"massBalanceFlux":0,"iteration":0,"deltaH":0},{"iceElevation":885.3886160129608,"bedElevation":0,"diffusivity_up":0,"flux_up":0,"diffusivity_down":0,"flux_down":0,"totalFlux":0,"massBalanceFlux":0,"iteration":0,"deltaH":0},{"iceElevation":883.6192829280562,"bedElevation":0,"diffusivity_up":0,"flux_up":0,"diffusivity_down":0,"flux_down":0,"totalFlux":0,"massBalanceFlux":0,"iteration":0,"deltaH":0},{"iceElevation":881.816426898265,"bedElevation":0,"diffusivity_up":0,"flux_up":0,"diffusivity_down":0,"flux_down":0,"totalFlux":0,"massBalanceFlux":0,"iteration":0,"deltaH":0},{"iceElevation":879.9805699922268,"bedElevation":0,"diffusivity_up":0,"flux_up":0,"diffusivity_down":0,"flux_down":0,"totalFlux":0,"massBalanceFlux":0,"iteration":0,"deltaH":0},{"iceElevation":878.1121780220298,"bedElevation":0,"diffusivity_up":0,"flux_up":0,"diffusivity_down":0,"flux_down":0,"totalFlux":0,"massBalanceFlux":0,"iteration":0,"deltaH":0},{"iceElevation":876.2116664750322,"bedElevation":0,"diffusivity_up":0,"flux_up":0,"diffusivity_down":0,"flux_down":0,"totalFlux":0,"massBalanceFlux":0,"iteration":0,"deltaH":0},{"iceElevation":874.2794055664692,"bedElevation":0,"diffusivity_up":0,"flux_up":0,"diffusivity_down":0,"flux_down":0,"totalFlux":0,"massBalanceFlux":0,"iteration":0,"deltaH":0},{"iceElevation":872.3157245689665,"bedElevation":0,"diffusivity_up":0,"flux_up":0,"diffusivity_down":0,"flux_down":0,"totalFlux":0,"massBalanceFlux":0,"iteration":0,"deltaH":0},{"iceElevation":870.3209155425675,"bedElevation":0,"diffusivity_up":0,"flux_up":0,"diffusivity_down":0,"flux_down":0,"totalFlux":0,"massBalanceFlux":0,"iteration":0,"deltaH":0},{"iceElevation":868.2952365640402,"bedElevation":0,"diffusivity_up":0,"flux_up":0,"diffusivity_down":0,"flux_down":0,"totalFlux":0,"massBalanceFlux":0,"iteration":0,"deltaH":0},{"iceElevation":866.2389145350489,"bedElevation":0,"diffusivity_up":0,"flux_up":0,"diffusivity_down":0,"flux_down":0,"totalFlux":0,"massBalanceFlux":0,"iteration":0,"deltaH":0},{"iceElevation":864.1521476338205,"bedElevation":0,"diffusivity_up":0,"flux_up":0,"diffusivity_down":0,"flux_down":0,"totalFlux":0,"massBalanceFlux":0,"iteration":0,"deltaH":0},{"iceElevation":862.035107463175,"bedElevation":0,"diffusivity_up":0,"flux_up":0,"diffusivity_down":0,"flux_down":0,"totalFlux":0,"massBalanceFlux":0,"iteration":0,"deltaH":0},{"iceElevation":859.8879409384563,"bedElevation":0,"diffusivity_up":0,"flux_up":0,"diffusivity_down":0,"flux_down":0,"totalFlux":0,"massBalanceFlux":0,"iteration":0,"deltaH":0},{"iceElevation":857.7107719514362,"bedElevation":0,"diffusivity_up":0,"flux_up":0,"diffusivity_down":0,"flux_down":0,"totalFlux":0,"massBalanceFlux":0,"iteration":0,"deltaH":0},{"iceElevation":855.5037028402578,"bedElevation":0,"diffusivity_up":0,"flux_up":0,"diffusivity_down":0,"flux_down":0,"totalFlux":0,"massBalanceFlux":0,"iteration":0,"deltaH":0},{"iceElevation":853.2668156906092,"bedElevation":0,"diffusivity_up":0,"flux_up":0,"diffusivity_down":0,"flux_down":0,"totalFlux":0,"massBalanceFlux":0,"iteration":0,"deltaH":0},{"iceElevation":851.0001734893414,"bedElevation":0,"diffusivity_up":0,"flux_up":0,"diffusivity_down":0,"flux_down":0,"totalFlux":0,"massBalanceFlux":0,"iteration":0,"deltaH":0},{"iceElevation":848.7038211484745,"bedElevation":0,"diffusivity_up":0,"flux_up":0,"diffusivity_down":0,"flux_down":0,"totalFlux":0,"massBalanceFlux":0,"iteration":0,"deltaH":0},{"iceElevation":846.377786414842,"bedElevation":0,"diffusivity_up":0,"flux_up":0,"diffusivity_down":0,"flux_down":0,"totalFlux":0,"massBalanceFlux":0,"iteration":0,"deltaH":0},{"iceElevation":844.0220806783755,"bedElevation":0,"diffusivity_up":0,"flux_up":0,"diffusivity_down":0,"flux_down":0,"totalFlux":0,"massBalanceFlux":0,"iteration":0,"deltaH":0},{"iceElevation":841.6366996901631,"bedElevation":0,"diffusivity_up":0,"flux_up":0,"diffusivity_down":0,"flux_down":0,"totalFlux":0,"massBalanceFlux":0,"iteration":0,"deltaH":0},{"iceElevation":839.2216241998459,"bedElevation":0,"diffusivity_up":0,"flux_up":0,"diffusivity_down":0,"flux_down":0,"totalFlux":0,"massBalanceFlux":0,"iteration":0,"deltaH":0},{"iceElevation":836.7768205205839,"bedElevation":0,"diffusivity_up":0,"flux_up":0,"diffusivity_down":0,"flux_down":0,"totalFlux":0,"massBalanceFlux":0,"iteration":0,"deltaH":0},{"iceElevation":834.3022410287094,"bedElevation":0,"diffusivity_up":0,"flux_up":0,"diffusivity_down":0,"flux_down":0,"totalFlux":0,"massBalanceFlux":0,"iteration":0,"deltaH":0},{"iceElevation":831.7978246042227,"bedElevation":0,"diffusivity_up":0,"flux_up":0,"diffusivity_down":0,"flux_down":0,"totalFlux":0,"massBalanceFlux":0,"iteration":0,"deltaH":0},{"iceElevation":829.2634970174693,"bedElevation":0,"diffusivity_up":0,"flux_up":0,"diffusivity_down":0,"flux_down":0,"totalFlux":0,"massBalanceFlux":0,"iteration":0,"deltaH":0},{"iceElevation":826.6991712666392,"bedElevation":0,"diffusivity_up":0,"flux_up":0,"diffusivity_down":0,"flux_down":0,"totalFlux":0,"massBalanceFlux":0,"iteration":0,"deltaH":0},{"iceElevation":824.1047478701157,"bedElevation":0,"diffusivity_up":0,"flux_up":0,"diffusivity_down":0,"flux_down":0,"totalFlux":0,"massBalanceFlux":0,"iteration":0,"deltaH":0},{"iceElevation":821.480115117184,"bedElevation":0,"diffusivity_up":0,"flux_up":0,"diffusivity_down":0,"flux_down":0,"totalFlux":0,"massBalanceFlux":0,"iteration":0,"deltaH":0},{"iceElevation":818.8251492801459,"bedElevation":0,"diffusivity_up":0,"flux_up":0,"diffusivity_down":0,"flux_down":0,"totalFlux":0,"massBalanceFlux":0,"iteration":0,"deltaH":0},{"iceElevation":816.1397147904919,"bedElevation":0,"diffusivity_up":0,"flux_up":0,"diffusivity_down":0,"flux_down":0,"totalFlux":0,"massBalanceFlux":0,"iteration":0,"deltaH":0},{"iceElevation":813.4236643814285,"bedElevation":0,"diffusivity_up":0,"flux_up":0,"diffusivity_down":0,"flux_down":0,"totalFlux":0,"massBalanceFlux":0,"iteration":0,"deltaH":0},{"iceElevation":810.676839198747,"bedElevation":0,"diffusivity_up":0,"flux_up":0,"diffusivity_down":0,"flux_down":0,"totalFlux":0,"massBalanceFlux":0,"iteration":0,"deltaH":0},{"iceElevation":807.8990688817482,"bedElevation":0,"diffusivity_up":0,"flux_up":0,"diffusivity_down":0,"flux_down":0,"totalFlux":0,"massBalanceFlux":0,"iteration":0,"deltaH":0},{"iceElevation":805.0901716156875,"bedElevation":0,"diffusivity_up":0,"flux_up":0,"diffusivity_down":0,"flux_down":0,"totalFlux":0,"massBalanceFlux":0,"iteration":0,"deltaH":0},{"iceElevation":802.2499541569861,"bedElevation":0,"diffusivity_up":0,"flux_up":0,"diffusivity_down":0,"flux_down":0,"totalFlux":0,"massBalanceFlux":0,"iteration":0,"deltaH":0},{"iceElevation":799.3782118322541,"bedElevation":0,"diffusivity_up":0,"flux_up":0,"diffusivity_down":0,"flux_down":0,"totalFlux":0,"massBalanceFlux":0,"iteration":0,"deltaH":0},{"iceElevation":796.4747285119912,"bedElevation":0,"diffusivity_up":0,"flux_up":0,"diffusivity_down":0,"flux_down":0,"totalFlux":0,"massBalanceFlux":0,"iteration":0,"deltaH":0},{"iceElevation":793.5392765596598,"bedElevation":0,"diffusivity_up":0,"flux_up":0,"diffusivity_down":0,"flux_down":0,"totalFlux":0,"massBalanceFlux":0,"iteration":0,"deltaH":0},{"iceElevation":790.5716167566776,"bedElevation":0,"diffusivity_up":0,"flux_up":0,"diffusivity_down":0,"flux_down":0,"totalFlux":0,"massBalanceFlux":0,"iteration":0,"deltaH":0},{"iceElevation":787.5714982037298,"bedElevation":0,"diffusivity_up":0,"flux_up":0,"diffusivity_down":0,"flux_down":0,"totalFlux":0,"massBalanceFlux":0,"iteration":0,"deltaH":0},{"iceElevation":784.538658198668,"bedElevation":0,"diffusivity_up":0,"flux_up":0,"diffusivity_down":0,"flux_down":0,"totalFlux":0,"massBalanceFlux":0,"iteration":0,"deltaH":0},{"iceElevation":781.4728220911363,"bedElevation":0,"diffusivity_up":0,"flux_up":0,"diffusivity_down":0,"flux_down":0,"totalFlux":0,"massBalanceFlux":0,"iteration":0,"deltaH":0},{"iceElevation":778.3737031139431,"bedElevation":0,"diffusivity_up":0,"flux_up":0,"diffusivity_down":0,"flux_down":0,"totalFlux":0,"massBalanceFlux":0,"iteration":0,"deltaH":0},{"iceElevation":775.2410021910786,"bedElevation":0,"diffusivity_up":0,"flux_up":0,"diffusivity_down":0,"flux_down":0,"totalFlux":0,"massBalanceFlux":0,"iteration":0,"deltaH":0},{"iceElevation":772.0744077221678,"bedElevation":0,"diffusivity_up":0,"flux_up":0,"diffusivity_down":0,"flux_down":0,"totalFlux":0,"massBalanceFlux":0,"iteration":0,"deltaH":0},{"iceElevation":768.8735953430302,"bedElevation":0,"diffusivity_up":0,"flux_up":0,"diffusivity_down":0,"flux_down":0,"totalFlux":0,"massBalanceFlux":0,"iteration":0,"deltaH":0},{"iceElevation":765.6382276619097,"bedElevation":0,"diffusivity_up":0,"flux_up":0,"diffusivity_down":0,"flux_down":0,"totalFlux":0,"massBalanceFlux":0,"iteration":0,"deltaH":0},{"iceElevation":762.367953970828,"bedElevation":0,"diffusivity_up":0,"flux_up":0,"diffusivity_down":0,"flux_down":0,"totalFlux":0,"massBalanceFlux":0,"iteration":0,"deltaH":0},{"iceElevation":759.0624099313937,"bedElevation":0,"diffusivity_up":0,"flux_up":0,"diffusivity_down":0,"flux_down":0,"totalFlux":0,"massBalanceFlux":0,"iteration":0,"deltaH":0},{"iceElevation":755.721217234294,"bedElevation":0,"diffusivity_up":0,"flux_up":0,"diffusivity_down":0,"flux_down":0,"totalFlux":0,"massBalanceFlux":0,"iteration":0,"deltaH":0},{"iceElevation":752.3439832315664,"bedElevation":0,"diffusivity_up":0,"flux_up":0,"diffusivity_down":0,"flux_down":0,"totalFlux":0,"massBalanceFlux":0,"iteration":0,"deltaH":0},{"iceElevation":748.9303005406343,"bedElevation":0,"diffusivity_up":0,"flux_up":0,"diffusivity_down":0,"flux_down":0,"totalFlux":0,"massBalanceFlux":0,"iteration":0,"deltaH":0},{"iceElevation":745.4797466189528,"bedElevation":0,"diffusivity_up":0,"flux_up":0,"diffusivity_down":0,"flux_down":0,"totalFlux":0,"massBalanceFlux":0,"iteration":0,"deltaH":0},{"iceElevation":741.9918833079843,"bedElevation":0,"diffusivity_up":0,"flux_up":0,"diffusivity_down":0,"flux_down":0,"totalFlux":0,"massBalanceFlux":0,"iteration":0,"deltaH":0},{"iceElevation":738.4662563450722,"bedElevation":0,"diffusivity_up":0,"flux_up":0,"diffusivity_down":0,"flux_down":0,"totalFlux":0,"massBalanceFlux":0,"iteration":0,"deltaH":0},{"iceElevation":734.9023948416391,"bedElevation":0,"diffusivity_up":0,"flux_up":0,"diffusivity_down":0,"flux_down":0,"totalFlux":0,"massBalanceFlux":0,"iteration":0,"deltaH":0},{"iceElevation":731.2998107259652,"bedElevation":0,"diffusivity_up":0,"flux_up":0,"diffusivity_down":0,"flux_down":0,"totalFlux":0,"massBalanceFlux":0,"iteration":0,"deltaH":0},{"iceElevation":727.6579981486374,"bedElevation":0,"diffusivity_up":0,"flux_up":0,"diffusivity_down":0,"flux_down":0,"totalFlux":0,"massBalanceFlux":0,"iteration":0,"deltaH":0},{"iceElevation":723.976432848568,"bedElevation":0,"diffusivity_up":0,"flux_up":0,"diffusivity_down":0,"flux_down":0,"totalFlux":0,"massBalanceFlux":0,"iteration":0,"deltaH":0},{"iceElevation":720.254571477287,"bedElevation":0,"diffusivity_up":0,"flux_up":0,"diffusivity_down":0,"flux_down":0,"totalFlux":0,"massBalanceFlux":0,"iteration":0,"deltaH":0},{"iceElevation":716.4918508789888,"bedElevation":0,"diffusivity_up":0,"flux_up":0,"diffusivity_down":0,"flux_down":0,"totalFlux":0,"massBalanceFlux":0,"iteration":0,"deltaH":0},{"iceElevation":712.6876873235851,"bedElevation":0,"diffusivity_up":0,"flux_up":0,"diffusivity_down":0,"flux_down":0,"totalFlux":0,"massBalanceFlux":0,"iteration":0,"deltaH":0},{"iceElevation":708.8414756897548,"bedElevation":0,"diffusivity_up":0,"flux_up":0,"diffusivity_down":0,"flux_down":0,"totalFlux":0,"massBalanceFlux":0,"iteration":0,"deltaH":0},{"iceElevation":704.9525885947057,"bedElevation":0,"diffusivity_up":0,"flux_up":0,"diffusivity_down":0,"flux_down":0,"totalFlux":0,"massBalanceFlux":0,"iteration":0,"deltaH":0},{"iceElevation":701.020375467055,"bedElevation":0,"diffusivity_up":0,"flux_up":0,"diffusivity_down":0,"flux_down":0,"totalFlux":0,"massBalanceFlux":0,"iteration":0,"deltaH":0},{"iceElevation":697.0441615589035,"bedElevation":0,"diffusivity_up":0,"flux_up":0,"diffusivity_down":0,"flux_down":0,"totalFlux":0,"massBalanceFlux":0,"iteration":0,"deltaH":0},{"iceElevation":693.0232468928085,"bedElevation":0,"diffusivity_up":0,"flux_up":0,"diffusivity_down":0,"flux_down":0,"totalFlux":0,"massBalanceFlux":0,"iteration":0,"deltaH":0},{"iceElevation":688.9569051389585,"bedElevation":0,"diffusivity_up":0,"flux_up":0,"diffusivity_down":0,"flux_down":0,"totalFlux":0,"massBalanceFlux":0,"iteration":0,"deltaH":0},{"iceElevation":684.8443824174072,"bedElevation":0,"diffusivity_up":0,"flux_up":0,"diffusivity_down":0,"flux_down":0,"totalFlux":0,"massBalanceFlux":0,"iteration":0,"deltaH":0},{"iceElevation":680.6848960197308,"bedElevation":0,"diffusivity_up":0,"flux_up":0,"diffusivity_down":0,"flux_down":0,"totalFlux":0,"massBalanceFlux":0,"iteration":0,"deltaH":0},{"iceElevation":676.4776330439319,"bedElevation":0,"diffusivity_up":0,"flux_up":0,"diffusivity_down":0,"flux_down":0,"totalFlux":0,"massBalanceFlux":0,"iteration":0,"deltaH":0},{"iceElevation":672.2217489358085,"bedElevation":0,"diffusivity_up":0,"flux_up":0,"diffusivity_down":0,"flux_down":0,"totalFlux":0,"massBalanceFlux":0,"iteration":0,"deltaH":0},{"iceElevation":667.9163659293393,"bedElevation":0,"diffusivity_up":0,"flux_up":0,"diffusivity_down":0,"flux_down":0,"totalFlux":0,"massBalanceFlux":0,"iteration":0,"deltaH":0},{"iceElevation":663.5605713778905,"bedElevation":0,"diffusivity_up":0,"flux_up":0,"diffusivity_down":0,"flux_down":0,"totalFlux":0,"massBalanceFlux":0,"iteration":0,"deltaH":0},{"iceElevation":659.1534159672241,"bedElevation":0,"diffusivity_up":0,"flux_up":0,"diffusivity_down":0,"flux_down":0,"totalFlux":0,"massBalanceFlux":0,"iteration":0,"deltaH":0},{"iceElevation":654.6939118003617,"bedElevation":0,"diffusivity_up":0,"flux_up":0,"diffusivity_down":0,"flux_down":0,"totalFlux":0,"massBalanceFlux":0,"iteration":0,"deltaH":0},{"iceElevation":650.1810303433228,"bedElevation":0,"diffusivity_up":0,"flux_up":0,"diffusivity_down":0,"flux_down":0,"totalFlux":0,"massBalanceFlux":0,"iteration":0,"deltaH":0},{"iceElevation":645.6137002196027,"bedElevation":0,"diffusivity_up":0,"flux_up":0,"diffusivity_down":0,"flux_down":0,"totalFlux":0,"massBalanceFlux":0,"iteration":0,"deltaH":0},{"iceElevation":640.9908048399517,"bedElevation":0,"diffusivity_up":0,"flux_up":0,"diffusivity_down":0,"flux_down":0,"totalFlux":0,"massBalanceFlux":0,"iteration":0,"deltaH":0},{"iceElevation":636.311179852563,"bedElevation":0,"diffusivity_up":0,"flux_up":0,"diffusivity_down":0,"flux_down":0,"totalFlux":0,"massBalanceFlux":0,"iteration":0,"deltaH":0},{"iceElevation":631.5736103971259,"bedElevation":0,"diffusivity_up":0,"flux_up":0,"diffusivity_down":0,"flux_down":0,"totalFlux":0,"massBalanceFlux":0,"iteration":0,"deltaH":0},{"iceElevation":626.7768281443489,"bedElevation":0,"diffusivity_up":0,"flux_up":0,"diffusivity_down":0,"flux_down":0,"totalFlux":0,"massBalanceFlux":0,"iteration":0,"deltaH":0},{"iceElevation":621.9195081004566,"bedElevation":0,"diffusivity_up":0,"flux_up":0,"diffusivity_down":0,"flux_down":0,"totalFlux":0,"massBalanceFlux":0,"iteration":0,"deltaH":0},{"iceElevation":617.0002651537827,"bedElevation":0,"diffusivity_up":0,"flux_up":0,"diffusivity_down":0,"flux_down":0,"totalFlux":0,"massBalanceFlux":0,"iteration":0,"deltaH":0},{"iceElevation":612.0176503378837,"bedElevation":0,"diffusivity_up":0,"flux_up":0,"diffusivity_down":0,"flux_down":0,"totalFlux":0,"massBalanceFlux":0,"iteration":0,"deltaH":0},{"iceElevation":606.9701467825142,"bedElevation":0,"diffusivity_up":0,"flux_up":0,"diffusivity_down":0,"flux_down":0,"totalFlux":0,"massBalanceFlux":0,"iteration":0,"deltaH":0},{"iceElevation":601.8561653203016,"bedElevation":0,"diffusivity_up":0,"flux_up":0,"diffusivity_down":0,"flux_down":0,"totalFlux":0,"massBalanceFlux":0,"iteration":0,"deltaH":0},{"iceElevation":596.6740397129332,"bedElevation":0,"diffusivity_up":0,"flux_up":0,"diffusivity_down":0,"flux_down":0,"totalFlux":0,"massBalanceFlux":0,"iteration":0,"deltaH":0},{"iceElevation":591.4220214560752,"bedElevation":0,"diffusivity_up":0,"flux_up":0,"diffusivity_down":0,"flux_down":0,"totalFlux":0,"massBalanceFlux":0,"iteration":0,"deltaH":0},{"iceElevation":586.0982741169391,"bedElevation":0,"diffusivity_up":0,"flux_up":0,"diffusivity_down":0,"flux_down":0,"totalFlux":0,"massBalanceFlux":0,"iteration":0,"deltaH":0},{"iceElevation":580.7008671523183,"bedElevation":0,"diffusivity_up":0,"flux_up":0,"diffusivity_down":0,"flux_down":0,"totalFlux":0,"massBalanceFlux":0,"iteration":0,"deltaH":0},{"iceElevation":575.2277691478607,"bedElevation":0,"diffusivity_up":0,"flux_up":0,"diffusivity_down":0,"flux_down":0,"totalFlux":0,"massBalanceFlux":0,"iteration":0,"deltaH":0},{"iceElevation":569.6768404111706,"bedElevation":0,"diffusivity_up":0,"flux_up":0,"diffusivity_down":0,"flux_down":0,"totalFlux":0,"massBalanceFlux":0,"iteration":0,"deltaH":0},{"iceElevation":564.04582484183,"bedElevation":0,"diffusivity_up":0,"flux_up":0,"diffusivity_down":0,"flux_down":0,"totalFlux":0,"massBalanceFlux":0,"iteration":0,"deltaH":0},{"iceElevation":558.3323409903444,"bedElevation":0,"diffusivity_up":0,"flux_up":0,"diffusivity_down":0,"flux_down":0,"totalFlux":0,"massBalanceFlux":0,"iteration":0,"deltaH":0},{"iceElevation":552.5338722050492,"bedElevation":0,"diffusivity_up":0,"flux_up":0,"diffusivity_down":0,"flux_down":0,"totalFlux":0,"massBalanceFlux":0,"iteration":0,"deltaH":0},{"iceElevation":546.6477557507908,"bedElevation":0,"diffusivity_up":0,"flux_up":0,"diffusivity_down":0,"flux_down":0,"totalFlux":0,"massBalanceFlux":0,"iteration":0,"deltaH":0},{"iceElevation":540.6711707652555,"bedElevation":0,"diffusivity_up":0,"flux_up":0,"diffusivity_down":0,"flux_down":0,"totalFlux":0,"massBalanceFlux":0,"iteration":0,"deltaH":0},{"iceElevation":534.6011248976107,"bedElevation":0,"diffusivity_up":0,"flux_up":0,"diffusivity_down":0,"flux_down":0,"totalFlux":0,"massBalanceFlux":0,"iteration":0,"deltaH":0},{"iceElevation":528.4344394489449,"bedElevation":0,"diffusivity_up":0,"flux_up":0,"diffusivity_down":0,"flux_down":0,"totalFlux":0,"massBalanceFlux":0,"iteration":0,"deltaH":0},{"iceElevation":522.1677328039838,"bedElevation":0,"diffusivity_up":0,"flux_up":0,"diffusivity_down":0,"flux_down":0,"totalFlux":0,"massBalanceFlux":0,"iteration":0,"deltaH":0},{"iceElevation":515.7974019076414,"bedElevation":0,"diffusivity_up":0,"flux_up":0,"diffusivity_down":0,"flux_down":0,"totalFlux":0,"massBalanceFlux":0,"iteration":0,"deltaH":0},{"iceElevation":509.31960149678815,"bedElevation":0,"diffusivity_up":0,"flux_up":0,"diffusivity_down":0,"flux_down":0,"totalFlux":0,"massBalanceFlux":0,"iteration":0,"deltaH":0},{"iceElevation":502.7302207454566,"bedElevation":0,"diffusivity_up":0,"flux_up":0,"diffusivity_down":0,"flux_down":0,"totalFlux":0,"massBalanceFlux":0,"iteration":0,"deltaH":0},{"iceElevation":496.02485691840906,"bedElevation":0,"diffusivity_up":0,"flux_up":0,"diffusivity_down":0,"flux_down":0,"totalFlux":0,"massBalanceFlux":0,"iteration":0,"deltaH":0},{"iceElevation":489.1987855507488,"bedElevation":0,"diffusivity_up":0,"flux_up":0,"diffusivity_down":0,"flux_down":0,"totalFlux":0,"massBalanceFlux":0,"iteration":0,"deltaH":0},{"iceElevation":482.24692657651616,"bedElevation":0,"diffusivity_up":0,"flux_up":0,"diffusivity_down":0,"flux_down":0,"totalFlux":0,"massBalanceFlux":0,"iteration":0,"deltaH":0},{"iceElevation":475.1638057123112,"bedElevation":0,"diffusivity_up":0,"flux_up":0,"diffusivity_down":0,"flux_down":0,"totalFlux":0,"massBalanceFlux":0,"iteration":0,"deltaH":0},{"iceElevation":467.94351025687524,"bedElevation":0,"diffusivity_up":0,"flux_up":0,"diffusivity_down":0,"flux_down":0,"totalFlux":0,"massBalanceFlux":0,"iteration":0,"deltaH":0},{"iceElevation":460.57963828626913,"bedElevation":0,"diffusivity_up":0,"flux_up":0,"diffusivity_down":0,"flux_down":0,"totalFlux":0,"massBalanceFlux":0,"iteration":0,"deltaH":0},{"iceElevation":453.06523999621976,"bedElevation":0,"diffusivity_up":0,"flux_up":0,"diffusivity_down":0,"flux_down":0,"totalFlux":0,"massBalanceFlux":0,"iteration":0,"deltaH":0},{"iceElevation":445.39274965421043,"bedElevation":0,"diffusivity_up":0,"flux_up":0,"diffusivity_down":0,"flux_down":0,"totalFlux":0,"massBalanceFlux":0,"iteration":0,"deltaH":0},{"iceElevation":437.5539062548219,"bedElevation":0,"diffusivity_up":0,"flux_up":0,"diffusivity_down":0,"flux_down":0,"totalFlux":0,"massBalanceFlux":0,"iteration":0,"deltaH":0},{"iceElevation":429.53966049658544,"bedElevation":0,"diffusivity_up":0,"flux_up":0,"diffusivity_down":0,"flux_down":0,"totalFlux":0,"massBalanceFlux":0,"iteration":0,"deltaH":0},{"iceElevation":421.34006508115993,"bedElevation":0,"diffusivity_up":0,"flux_up":0,"diffusivity_down":0,"flux_down":0,"totalFlux":0,"massBalanceFlux":0,"iteration":0,"deltaH":0},{"iceElevation":412.9441445257786,"bedElevation":0,"diffusivity_up":0,"flux_up":0,"diffusivity_down":0,"flux_down":0,"totalFlux":0,"massBalanceFlux":0,"iteration":0,"deltaH":0},{"iceElevation":404.3397396066697,"bedElevation":0,"diffusivity_up":0,"flux_up":0,"diffusivity_down":0,"flux_down":0,"totalFlux":0,"massBalanceFlux":0,"iteration":0,"deltaH":0},{"iceElevation":395.5133201130742,"bedElevation":0,"diffusivity_up":0,"flux_up":0,"diffusivity_down":0,"flux_down":0,"totalFlux":0,"massBalanceFlux":0,"iteration":0,"deltaH":0},{"iceElevation":386.44975764125667,"bedElevation":0,"diffusivity_up":0,"flux_up":0,"diffusivity_down":0,"flux_down":0,"totalFlux":0,"massBalanceFlux":0,"iteration":0,"deltaH":0},{"iceElevation":377.1320474784762,"bedElevation":0,"diffusivity_up":0,"flux_up":0,"diffusivity_down":0,"flux_down":0,"totalFlux":0,"massBalanceFlux":0,"iteration":0,"deltaH":0},{"iceElevation":367.54096489290816,"bedElevation":0,"diffusivity_up":0,"flux_up":0,"diffusivity_down":0,"flux_down":0,"totalFlux":0,"massBalanceFlux":0,"iteration":0,"deltaH":0},{"iceElevation":357.65463586040306,"bedElevation":0,"diffusivity_up":0,"flux_up":0,"diffusivity_down":0,"flux_down":0,"totalFlux":0,"massBalanceFlux":0,"iteration":0,"deltaH":0},{"iceElevation":347.4479946493435,"bedElevation":0,"diffusivity_up":0,"flux_up":0,"diffusivity_down":0,"flux_down":0,"totalFlux":0,"massBalanceFlux":0,"iteration":0,"deltaH":0},{"iceElevation":336.8920895193388,"bedElevation":0,"diffusivity_up":0,"flux_up":0,"diffusivity_down":0,"flux_down":0,"totalFlux":0,"massBalanceFlux":0,"iteration":0,"deltaH":0},{"iceElevation":325.95318105881154,"bedElevation":0,"diffusivity_up":0,"flux_up":0,"diffusivity_down":0,"flux_down":0,"totalFlux":0,"massBalanceFlux":0,"iteration":0,"deltaH":0},{"iceElevation":314.5915520214689,"bedElevation":0,"diffusivity_up":0,"flux_up":0,"diffusivity_down":0,"flux_down":0,"totalFlux":0,"massBalanceFlux":0,"iteration":0,"deltaH":0},{"iceElevation":302.7599070968735,"bedElevation":0,"diffusivity_up":0,"flux_up":0,"diffusivity_down":0,"flux_down":0,"totalFlux":0,"massBalanceFlux":0,"iteration":0,"deltaH":0},{"iceElevation":290.40117543936606,"bedElevation":0,"diffusivity_up":0,"flux_up":0,"diffusivity_down":0,"flux_down":0,"totalFlux":0,"massBalanceFlux":0,"iteration":0,"deltaH":0},{"iceElevation":277.445418569719,"bedElevation":0,"diffusivity_up":0,"flux_up":0,"diffusivity_down":0,"flux_down":0,"totalFlux":0,"massBalanceFlux":0,"iteration":0,"deltaH":0},{"iceElevation":263.8053536308458,"bedElevation":0,"diffusivity_up":0,"flux_up":0,"diffusivity_down":0,"flux_down":0,"totalFlux":0,"massBalanceFlux":0,"iteration":0,"deltaH":0},{"iceElevation":249.36964921424328,"bedElevation":0,"diffusivity_up":0,"flux_up":0,"diffusivity_down":0,"flux_down":0,"totalFlux":0,"massBalanceFlux":0,"iteration":0,"deltaH":0},{"iceElevation":233.99246809568325,"bedElevation":0,"diffusivity_up":0,"flux_up":0,"diffusivity_down":0,"flux_down":0,"totalFlux":0,"massBalanceFlux":0,"iteration":0,"deltaH":0},{"iceElevation":217.47631720050816,"bedElevation":0,"diffusivity_up":0,"flux_up":0,"diffusivity_down":0,"flux_down":0,"totalFlux":0,"massBalanceFlux":0,"iteration":0,"deltaH":0},{"iceElevation":199.54208129277245,"bedElevation":0,"diffusivity_up":0,"flux_up":0,"diffusivity_down":0,"flux_down":0,"totalFlux":0,"massBalanceFlux":0,"iteration":0,"deltaH":0},{"iceElevation":179.77213331829668,"bedElevation":0,"diffusivity_up":0,"flux_up":0,"diffusivity_down":0,"flux_down":0,"totalFlux":0,"massBalanceFlux":0,"iteration":0,"deltaH":0},{"iceElevation":157.48927294038486,"bedElevation":0,"diffusivity_up":0,"flux_up":0,"diffusivity_down":0,"flux_down":0,"totalFlux":0,"massBalanceFlux":0,"iteration":0,"deltaH":0},{"iceElevation":131.45149140919312,"bedElevation":0,"diffusivity_up":0,"flux_up":0,"diffusivity_down":0,"flux_down":0,"totalFlux":0,"massBalanceFlux":0,"iteration":0,"deltaH":0},{"iceElevation":98.82260521122474,"bedElevation":0,"diffusivity_up":0,"flux_up":0,"diffusivity_down":0,"flux_down":0,"totalFlux":0,"massBalanceFlux":0,"iteration":0,"deltaH":0},{"iceElevation":0,"bedElevation":0,"diffusivity_up":0,"flux_up":0,"diffusivity_down":0,"flux_down":0,"totalFlux":0,"massBalanceFlux":0,"iteration":0,"deltaH":0},{"iceElevation":0,"bedElevation":0,"diffusivity_up":0,"flux_up":0,"diffusivity_down":0,"flux_down":0,"totalFlux":0,"massBalanceFlux":0,"iteration":0,"deltaH":0},{"iceElevation":0,"bedElevation":0,"diffusivity_up":0,"flux_up":0,"diffusivity_down":0,"flux_down":0,"totalFlux":0,"massBalanceFlux":0,"iteration":0,"deltaH":0},{"iceElevation":0,"bedElevation":0,"diffusivity_up":0,"flux_up":0,"diffusivity_down":0,"flux_down":0,"totalFlux":0,"massBalanceFlux":0,"iteration":0,"deltaH":0},{"iceElevation":0,"bedElevation":0,"diffusivity_up":0,"flux_up":0,"diffusivity_down":0,"flux_down":0,"totalFlux":0,"massBalanceFlux":0,"iteration":0,"deltaH":0},{"iceElevation":0,"bedElevation":0,"diffusivity_up":0,"flux_up":0,"diffusivity_down":0,"flux_down":0,"totalFlux":0,"massBalanceFlux":0,"iteration":0,"deltaH":0},{"iceElevation":0,"bedElevation":0,"diffusivity_up":0,"flux_up":0,"diffusivity_down":0,"flux_down":0,"totalFlux":0,"massBalanceFlux":0,"iteration":0,"deltaH":0},{"iceElevation":0,"bedElevation":0,"diffusivity_up":0,"flux_up":0,"diffusivity_down":0,"flux_down":0,"totalFlux":0,"massBalanceFlux":0,"iteration":0,"deltaH":0},{"iceElevation":0,"bedElevation":0,"diffusivity_up":0,"flux_up":0,"diffusivity_down":0,"flux_down":0,"totalFlux":0,"massBalanceFlux":0,"iteration":0,"deltaH":0},{"iceElevation":0,"bedElevation":0,"diffusivity_up":0,"flux_up":0,"diffusivity_down":0,"flux_down":0,"totalFlux":0,"massBalanceFlux":0,"iteration":0,"deltaH":0},{"iceElevation":0,"bedElevation":0,"diffusivity_up":0,"flux_up":0,"diffusivity_down":0,"flux_down":0,"totalFlux":0,"massBalanceFlux":0,"iteration":0,"deltaH":0},{"iceElevation":0,"bedElevation":0,"diffusivity_up":0,"flux_up":0,"diffusivity_down":0,"flux_down":0,"totalFlux":0,"massBalanceFlux":0,"iteration":0,"deltaH":0},{"iceElevation":0,"bedElevation":0,"diffusivity_up":0,"flux_up":0,"diffusivity_down":0,"flux_down":0,"totalFlux":0,"massBalanceFlux":0,"iteration":0,"deltaH":0},{"iceElevation":0,"bedElevation":0,"diffusivity_up":0,"flux_up":0,"diffusivity_down":0,"flux_down":0,"totalFlux":0,"massBalanceFlux":0,"iteration":0,"deltaH":0},{"iceElevation":0,"bedElevation":0,"diffusivity_up":0,"flux_up":0,"diffusivity_down":0,"flux_down":0,"totalFlux":0,"massBalanceFlux":0,"iteration":0,"deltaH":0},{"iceElevation":0,"bedElevation":0,"diffusivity_up":0,"flux_up":0,"diffusivity_down":0,"flux_down":0,"totalFlux":0,"massBalanceFlux":0,"iteration":0,"deltaH":0},{"iceElevation":0,"bedElevation":0,"diffusivity_up":0,"flux_up":0,"diffusivity_down":0,"flux_down":0,"totalFlux":0,"massBalanceFlux":0,"iteration":0,"deltaH":0},{"iceElevation":0,"bedElevation":0,"diffusivity_up":0,"flux_up":0,"diffusivity_down":0,"flux_down":0,"totalFlux":0,"massBalanceFlux":0,"iteration":0,"deltaH":0},{"iceElevation":0,"bedElevation":0,"diffusivity_up":0,"flux_up":0,"diffusivity_down":0,"flux_down":0,"totalFlux":0,"massBalanceFlux":0,"iteration":0,"deltaH":0},{"iceElevation":0,"bedElevation":0,"diffusivity_up":0,"flux_up":0,"diffusivity_down":0,"flux_down":0,"totalFlux":0,"massBalanceFlux":0,"iteration":0,"deltaH":0},{"iceElevation":0,"bedElevation":0,"diffusivity_up":0,"flux_up":0,"diffusivity_down":0,"flux_down":0,"totalFlux":0,"massBalanceFlux":0,"iteration":0,"deltaH":0},{"iceElevation":0,"bedElevation":0,"diffusivity_up":0,"flux_up":0,"diffusivity_down":0,"flux_down":0,"totalFlux":0,"massBalanceFlux":0,"iteration":0,"deltaH":0},{"iceElevation":0,"bedElevation":0,"diffusivity_up":0,"flux_up":0,"diffusivity_down":0,"flux_down":0,"totalFlux":0,"massBalanceFlux":0,"iteration":0,"deltaH":0},{"iceElevation":0,"bedElevation":0,"diffusivity_up":0,"flux_up":0,"diffusivity_down":0,"flux_down":0,"totalFlux":0,"massBalanceFlux":0,"iteration":0,"deltaH":0},{"iceElevation":0,"bedElevation":0,"diffusivity_up":0,"flux_up":0,"diffusivity_down":0,"flux_down":0,"totalFlux":0,"massBalanceFlux":0,"iteration":0,"deltaH":0},{"iceElevation":0,"bedElevation":0,"diffusivity_up":0,"flux_up":0,"diffusivity_down":0,"flux_down":0,"totalFlux":0,"massBalanceFlux":0,"iteration":0,"deltaH":0},{"iceElevation":0,"bedElevation":0,"diffusivity_up":0,"flux_up":0,"diffusivity_down":0,"flux_down":0,"totalFlux":0,"massBalanceFlux":0,"iteration":0,"deltaH":0},{"iceElevation":0,"bedElevation":0,"diffusivity_up":0,"flux_up":0,"diffusivity_down":0,"flux_down":0,"totalFlux":0,"massBalanceFlux":0,"iteration":0,"deltaH":0},{"iceElevation":0,"bedElevation":0,"diffusivity_up":0,"flux_up":0,"diffusivity_down":0,"flux_down":0,"totalFlux":0,"massBalanceFlux":0,"iteration":0,"deltaH":0},{"iceElevation":0,"bedElevation":0,"diffusivity_up":0,"flux_up":0,"diffusivity_down":0,"flux_down":0,"totalFlux":0,"massBalanceFlux":0,"iteration":0,"deltaH":0},{"iceElevation":0,"bedElevation":0,"diffusivity_up":0,"flux_up":0,"diffusivity_down":0,"flux_down":0,"totalFlux":0,"massBalanceFlux":0,"iteration":0,"deltaH":0},{"iceElevation":0,"bedElevation":0,"diffusivity_up":0,"flux_up":0,"diffusivity_down":0,"flux_down":0,"totalFlux":0,"massBalanceFlux":0,"iteration":0,"deltaH":0},{"iceElevation":0,"bedElevation":0,"diffusivity_up":0,"flux_up":0,"diffusivity_down":0,"flux_down":0,"totalFlux":0,"massBalanceFlux":0,"iteration":0,"deltaH":0},{"iceElevation":0,"bedElevation":0,"diffusivity_up":0,"flux_up":0,"diffusivity_down":0,"flux_down":0,"totalFlux":0,"massBalanceFlux":0,"iteration":0,"deltaH":0},{"iceElevation":0,"bedElevation":0,"diffusivity_up":0,"flux_up":0,"diffusivity_down":0,"flux_down":0,"totalFlux":0,"massBalanceFlux":0,"iteration":0,"deltaH":0},{"iceElevation":0,"bedElevation":0,"diffusivity_up":0,"flux_up":0,"diffusivity_down":0,"flux_down":0,"totalFlux":0,"massBalanceFlux":0,"iteration":0,"deltaH":0},{"iceElevation":0,"bedElevation":0,"diffusivity_up":0,"flux_up":0,"diffusivity_down":0,"flux_down":0,"totalFlux":0,"massBalanceFlux":0,"iteration":0,"deltaH":0},{"iceElevation":0,"bedElevation":0,"diffusivity_up":0,"flux_up":0,"diffusivity_down":0,"flux_down":0,"totalFlux":0,"massBalanceFlux":0,"iteration":0,"deltaH":0},{"iceElevation":0,"bedElevation":0,"diffusivity_up":0,"flux_up":0,"diffusivity_down":0,"flux_down":0,"totalFlux":0,"massBalanceFlux":0,"iteration":0,"deltaH":0},{"iceElevation":0,"bedElevation":0,"diffusivity_up":0,"flux_up":0,"diffusivity_down":0,"flux_down":0,"totalFlux":0,"massBalanceFlux":0,"iteration":0,"deltaH":0}],"fluxes":[-999.9685487938451,-1999.936107893603,-2999.8968144377504,-3999.838947181148,-4999.744925950175,-5999.591311473201,-6999.348805273817,-7998.982249631367,-8998.450627536084,-9997.707062674022,-10996.698819407671,-11995.367302761482,-12993.648058425137,-13991.470772730061,-14988.759272656658,-15985.431525819791,-16981.3996404749,-17976.569865508904,-18970.84259042317,-19964.11234537424,-20956.267801125166,-21947.191769053545,-22936.76120117809,-23924.847190136185,-24911.314969156912,-25896.023912124405,-26878.827533497297,-27859.573488389244,-28838.103572495722,-29814.253722140504,-30787.854014250475,-31758.72866636929,-32726.696036654008,-33691.56862384923,-34653.153067342326,-35611.25014708567,-36565.654783671635,-37516.156038274574,-38462.53711269754,-39404.575349315,-40342.042231129446,-41274.70338173475,-42202.31856532688,-43124.64168670642,-44041.420791252276,-44952.398064967485,-45857.309834439904,-46755.88656683947,-47647.85286995308,-48532.92749216298,-49410.82332241012,-50281.24739026875,-51143.900865877345,-51998.47905996658,-52844.671423855514,-53682.16154945548,-54510.627169258885,-55329.74015634521,-56139.16652436445,-56938.56642756337,-57727.59416074921,-58505.89815933097,-59273.12099926141,-60028.89939709756,-60772.86420995614,-61504.64043551956,-62223.84721202891,-62930.09781832978,-63622.999673793594,-64302.15433835114,-64967.157512526814,-65617.59903737003,-66253.06289450506,-66873.12720607653,-67477.36423481553,-68065.3403839778,-68636.61619734469,-69190.7463592738,-69727.27969461997,-70245.75916880151,-70745.72188772359,-71226.69909786929,-71688.21618617384,-72129.79268014722,-72550.9422477666,-72951.1726975221,-73329.98597841698,-73686.87817992539,-74021.33953202011,-74332.8544051385,-74620.90131020786,-74884.95289861785,-75124.47596219271,-75338.93143322678,-75527.77438444542,-75690.45402900912,-75826.41372048201,-75935.09095284928,-76015.91736049294,-76068.31871815845,-76091.7149410035,-76085.52008449857,-76049.14234447289,-75981.98405708015,-75883.44169877796,-75752.90588631602,-75589.76137669387,-75393.38706716163,-75163.15599520116,-74898.43533846457,-74598.58641478528,-74262.96468211406,-73890.91973851829,-73481.79532210513,-73034.92931101726,-72549.65372336953,-72025.29471720385,-71461.17259044047,-70856.60178080542,-70210.89086578703,-69523.34256255289,-68793.25372786178,-68019.91535798273,-67202.6125886158,-66340.62469474874,-65433.22509055519,-64479.681329254534,-63479.25510295529,-62431.202242466345,-61334.77271712954,-60189.21063455762,-58993.7542403999,-57747.635918026026,-56450.08218820668,-55100.31370868462,-53697.54527374536,-52240.985813656196,-50729.8383940284,-49163.30021507458,-47540.56261069831,-45860.81104742044,-44123.22512306416,-42326.978565157086,-40471.2392289672,-38555.169095037614,-36577.924266099886,-34538.65496312136,-32436.50552019779,-30270.614377837213,-28040.11407396147,-25744.131231643478,-23381.786541956542,-20952.194739412625,-18454.464565715054,-15887.698714515007,-13250.99374432766,-10543.43993758362,-7764.121077212096,-4912.114207902514,-1986.4911945544522,0,0,0,0,0,0,0,0,0,0,0,0,0,0,0,0,0,0,0,0,0,0,0,0,0,0,0,0,0,0,0,0,0,0,0,0,0,0,0]}